Frames/__init__.py
Frames/_about.py
Frames/clock.py
Frames/clock.pyi
Frames/_internal/core.py
Frames/_internal/core.pyi
frameclock-1.0.0.dist-info/licenses/LICENSE
frameclock-1.0.0.dist-info/METADATA
frameclock-1.0.0.dist-info/WHEEL
frameclock-1.0.0.dist-info/top_level.txt
frameclock-1.0.0.dist-info/RECORD
