Metadata-Version: 2.4
Name: frameclock
Version: 1.0.0
Summary: A lightweight Python frame counter and limiter library for small projects and simulations.
Author-email: Your Name <youremail@example.com>
License: MIT
Project-URL: Source, https://github.com/NeoZett/Frames
Project-URL: Tracker, https://github.com/NeoZett/Frames/issues
Keywords: frame,fps,timer,game,simulation,clock
Classifier: Programming Language :: Python :: 3
Classifier: License :: OSI Approved :: MIT License
Classifier: Operating System :: OS Independent
Classifier: Topic :: Software Development :: Libraries
Requires-Python: >=3.7
License-File: LICENSE
Dynamic: license-file
